mini_engine.py
mngine-1.0.0.dist-info/METADATA
mngine-1.0.0.dist-info/WHEEL
mngine-1.0.0.dist-info/top_level.txt
mngine-1.0.0.dist-info/RECORD
