Metadata-Version: 2.2
Name: mngine
Version: 1.0.0
Summary: Minimalistic game engine based on PyGame
Author: UShsrp
Dynamic: author
Dynamic: summary
